sphinx_simulink-0.0.1.dist-info/DESCRIPTION.rst
sphinx_simulink-0.0.1.dist-info/METADATA
sphinx_simulink-0.0.1.dist-info/RECORD
sphinx_simulink-0.0.1.dist-info/WHEEL
sphinx_simulink-0.0.1.dist-info/metadata.json
sphinx_simulink-0.0.1.dist-info/top_level.txt
sphinxsimulink/__init__.py
sphinxsimulink/metadata.py
sphinxsimulink/diagram/__init__.py
sphinxsimulink/diagram/application.py
sphinxsimulink/diagram/directives.py
sphinxsimulink/diagram/nodes.py
