Metadata-Version: 2.0
Name: sphinx-simulink
Version: 0.0.1
Summary: Sphinx plugin to include MATLAB/Simulink models into .rst
Home-page: https://github.com/dekalinowski/sphinx-simulink
Author: Dennis Edward Kalinowski
Author-email: dekalinowski@gmail.com
License: MIT
Keywords: sphinx documentation simulink
Platform: UNKNOWN
Classifier: Development Status :: 3 - Alpha
Classifier: Intended Audience :: Developers
Classifier: Intended Audience :: Science/Research
Classifier: Framework :: Sphinx
Classifier: Framework :: Sphinx :: Extension
Classifier: Topic :: Documentation
Classifier: Topic :: Documentation :: Sphinx
Classifier: Topic :: Software Development :: Documentation
Classifier: Topic :: Software Development :: Build Tools
Classifier: License :: OSI Approved :: MIT License
Classifier: Programming Language :: Python :: 3.4
Requires-Dist: docutils
Requires-Dist: sphinx
